README.md
setup.py
gluonbook/__init__.py
gluonbook/utils.py
gluonbook.egg-info/PKG-INFO
gluonbook.egg-info/SOURCES.txt
gluonbook.egg-info/dependency_links.txt
gluonbook.egg-info/requires.txt
gluonbook.egg-info/top_level.txt
gluonbook.egg-info/zip-safe