Metadata-Version: 1.0
Name: gluonbook
Version: 0.8.3
Summary: Gluon Book Utils
Home-page: https://github.com/mli/gluon-tutorials-zh
Author: Contributors
Author-email: mli@amazon.com
License: Apache-2.0
Platform: UNKNOWN
